image2hex/__init__.py
image2hex/cli.py
image2hex/uploader.py
image2hex-0.1.7.dist-info/licenses/LICENSE
image2hex-0.1.7.dist-info/METADATA
image2hex-0.1.7.dist-info/WHEEL
image2hex-0.1.7.dist-info/entry_points.txt
image2hex-0.1.7.dist-info/top_level.txt
image2hex-0.1.7.dist-info/RECORD
