Metadata-Version: 2.4
Name: image2hex
Version: 0.1.7
Summary: Parse image data to hex.
Author: oker
License: MIT License
Keywords: image,hex,parser,cli
Classifier: Programming Language :: Python :: 3
Classifier: Operating System :: POSIX :: Linux
Requires-Python: <3.10,>=3.6
License-File: LICENSE
Requires-Dist: requests<=2.27.1,>=2.22
Dynamic: license-file
